micoo/__init__.py
micoo/__main__.py
micoo/_version.py
micoo/config.py
micoo/logging_setup.py
micoo/main.py
micoo/py.typed
micoo-0.4.0.dist-info/METADATA
micoo-0.4.0.dist-info/WHEEL
micoo-0.4.0.dist-info/entry_points.txt
micoo-0.4.0.dist-info/licenses/LICENSE
micoo-0.4.0.dist-info/RECORD
