Metadata-Version: 2.4
Name: micoo
Version: 0.4.0
Summary: micoo is a command-line tool for easily accessing mise cookbooks
Project-URL: changelog, https://github.com/hasansezertasan/micoo/blob/main/CHANGELOG.md
Project-URL: documentation, https://github.com/hasansezertasan/micoo#readme
Project-URL: homepage, https://github.com/hasansezertasan/micoo
Project-URL: issues, https://github.com/hasansezertasan/micoo/issues
Project-URL: releasenotes, https://github.com/hasansezertasan/micoo/releases
Project-URL: source, https://github.com/hasansezertasan/micoo.git
Author-email: Hasan Sezer Taşan <hasansezertasan@gmail.com>
Maintainer-email: hasansezertasan <hasansezertasan@gmail.com>
License-Expression: MIT
License-File: LICENSE
Keywords: boilerplate,cli,command-line,cookbook,mise,scaffold,template
Classifier: Development Status :: 4 - Beta
Classifier: Environment :: Console
Classifier: Intended Audience :: Developers
Classifier: Intended Audience :: Information Technology
Classifier: Intended Audience :: System Administrators
Classifier: License :: OSI Approved :: MIT License
Classifier: Operating System :: OS Independent
Classifier: Programming Language :: Python
Classifier: Programming Language :: Python :: 3
Classifier: Programming Language :: Python :: 3 :: Only
Classifier: Programming Language :: Python :: 3.8
Classifier: Programming Language :: Python :: 3.9
Classifier: Programming Language :: Python :: 3.10
Classifier: Programming Language :: Python :: 3.11
Classifier: Programming Language :: Python :: 3.12
Classifier: Programming Language :: Python :: 3.13
Classifier: Programming Language :: Python :: Implementation :: CPython
Classifier: Programming Language :: Python :: Implementation :: PyPy
Classifier: Topic :: Internet
Classifier: Topic :: Software Development
Classifier: Topic :: Software Development :: Libraries
Classifier: Topic :: Software Development :: Libraries :: Python Modules
Classifier: Topic :: Terminals
Classifier: Typing :: Typed
Requires-Python: >=3.8
Requires-Dist: gitpython>=3.0.0
Requires-Dist: platformdirs>=4.0.0
Requires-Dist: pydantic-settings>=2.8.1
Requires-Dist: typer>=0.16.0
